codemind/__main__.py
codemind/cli.py
codemind-0.0.11.dist-info/licenses/LICENSE
codemind-0.0.11.dist-info/METADATA
codemind-0.0.11.dist-info/WHEEL
codemind-0.0.11.dist-info/entry_points.txt
codemind-0.0.11.dist-info/top_level.txt
codemind-0.0.11.dist-info/RECORD
