Metadata-Version: 2.4
Name: codemind
Version: 0.0.11
Summary: An API-first software development workspace powered by apibean and Jupyter.
License-File: LICENSE
Requires-Dist: apibean-jupyter
Requires-Dist: apibean-notebook
Requires-Dist: apibean-intercept
Requires-Dist: apibean-client
Dynamic: license-file
